azure_migrate/credentials.py
azure_migrate/migrate.py
azure_migrate-0.0.6.dist-info/LICENSE
azure_migrate-0.0.6.dist-info/METADATA
azure_migrate-0.0.6.dist-info/WHEEL
azure_migrate-0.0.6.dist-info/top_level.txt
azure_migrate-0.0.6.dist-info/RECORD
