Metadata-Version: 2.1
Name: azure-migrate
Version: 0.0.6
Summary: A package to management migrate azure
Home-page: https://github.com/alissonit/azure_migrate
Author: Alisson Castro
Author-email: alissoncastroskt@gmail.com
License: UNKNOWN
Project-URL: Source, https://github.com/alissonit/azure_migrate
Project-URL: Documentation, https://github.com/alissonit/azure_migrate/docs
Project-URL: Tracker, https://github.com/alissonit/azure_migrate/issues
Platform: UNKNOWN
Classifier: Programming Language :: Python :: 3
Classifier: License :: OSI Approved :: MIT License
Classifier: Operating System :: OS Independent
Requires-Python: >=3.6
